examples/__init__.py
examples/example_stringify_decorator.py
examples/example_stringify_info.py
strify/__init__.py
strify/config.py
strify/module_storage.py
strify/stringifiable.py
strify/stringify.py
strify/stringify_info.py
strify/replacing/__init__.py
strify/replacing/replacement.py
strify/replacing/replacer.py
strify/replacing/replacement_data/__init__.py
strify/replacing/replacement_data/attr_name.py
strify/replacing/replacement_data/func.py
strify/replacing/replacement_data/replacement_data.py
strify/utils/__init__.py
strify/utils/cached_property.py
strify/utils/small_funcs.py
strify/utils/types.py
strify-1.0.2.dist-info/LICENSE
strify-1.0.2.dist-info/METADATA
strify-1.0.2.dist-info/WHEEL
strify-1.0.2.dist-info/top_level.txt
strify-1.0.2.dist-info/RECORD
