Metadata-Version: 2.1
Name: strify
Version: 1.0.2
Summary: The library provides a lightweight API using which you can in a minute add a pattern processing function "stringify(pattern: str) -> str" to any class.
Home-page: https://gitlab.com/aduard.kononov/strify
Author: Eduard Konanau
Author-email: aduard.kononov@gmail.com
License: UNKNOWN
Platform: UNKNOWN
Classifier: Programming Language :: Python :: 3
Classifier: License :: OSI Approved :: MIT License
Classifier: Operating System :: OS Independent
Requires-Python: >=3.6
